MANIFEST.in
PKG-INFO
README
setup.cfg
setup.py
TurboFlot.egg-info/PKG-INFO
TurboFlot.egg-info/SOURCES.txt
TurboFlot.egg-info/dependency_links.txt
TurboFlot.egg-info/entry_points.txt
TurboFlot.egg-info/not-zip-safe
TurboFlot.egg-info/requires.txt
TurboFlot.egg-info/top_level.txt
turboflot/__init__.py
turboflot/widgets.py
turboflot/static/excanvas.min.js
turboflot/static/jquery.colorhelpers.min.js
turboflot/static/jquery.flot.crosshair.min.js
turboflot/static/jquery.flot.fillbetween.min.js
turboflot/static/jquery.flot.image.min.js
turboflot/static/jquery.flot.min.js
turboflot/static/jquery.flot.navigate.min.js
turboflot/static/jquery.flot.pie.min.js
turboflot/static/jquery.flot.resize.min.js
turboflot/static/jquery.flot.selection.min.js
turboflot/static/jquery.flot.stack.min.js
turboflot/static/jquery.flot.symbol.min.js
turboflot/static/jquery.flot.threshold.min.js
turboflot/static/jquery.min.js
turboflot/static/turboflot.css