Metadata-Version: 1.0
Name: TurboFlot
Version: 0.7.0
Summary: A TurboGears widget for Flot, a jQuery plotting library
Home-page: UNKNOWN
Author: Luke Macken
Author-email: lewk@csh.rit.edu
License: MIT
Keywords: turbogears.widgets
Platform: UNKNOWN
Classifier: Development Status :: 3 - Alpha
Classifier: Operating System :: OS Independent
Classifier: Programming Language :: Python
Classifier: Topic :: Software Development :: Libraries :: Python Modules
Classifier: Framework :: TurboGears
Classifier: Framework :: TurboGears :: Widgets
